pyusermanager_api/__init__.py
pyusermanager_api/_version.py
pyusermanager_api/api_configure.py
pyusermanager_api/api_misc.py
pyusermanager_api/api_permissions.py
pyusermanager_api/api_register.py
pyusermanager_api/api_routes.py
pyusermanager_api/api_sessions.py
pyusermanager_api/api_user.py
pyusermanager_api-0.0.5.dist-info/LICENSE
pyusermanager_api-0.0.5.dist-info/METADATA
pyusermanager_api-0.0.5.dist-info/WHEEL
pyusermanager_api-0.0.5.dist-info/top_level.txt
pyusermanager_api-0.0.5.dist-info/RECORD
