Metadata-Version: 2.1
Name: pyusermanager-api
Version: 0.0.5
Summary: Some Functions to manage a User Database and do stuff with it!
Home-page: https://github.com/Aurvandill/pyusermanager_api
Author: Ole Hannemann
Author-email: cerberus885@gmail.com
License: MIT
Platform: UNKNOWN
Classifier: Programming Language :: Python :: 3.0
Classifier: Programming Language :: Python :: 3.9
Classifier: Development Status :: 5 - Production/Stable
Classifier: License :: OSI Approved :: MIT License
Requires-Dist: pyusermanager
Requires-Dist: sanic
Requires-Dist: setuptools (>=45.0)
Requires-Dist: sws-webstuff
